PyTBot/__init__.py
PyTBot-0.2.dev1.dist-info/DESCRIPTION.rst
PyTBot-0.2.dev1.dist-info/METADATA
PyTBot-0.2.dev1.dist-info/RECORD
PyTBot-0.2.dev1.dist-info/WHEEL
PyTBot-0.2.dev1.dist-info/metadata.json
PyTBot-0.2.dev1.dist-info/top_level.txt
