Metadata-Version: 2.0
Name: PyTBot
Version: 0.2.dev1
Summary: A Pure Python Telegram Bot API library
Home-page: https://github.com/RRostami/PyTBot
Author: Ramtin Rostami
Author-email: ramtinrostami@gmail.com
License: MIT
Keywords: Telegram Bot api
Platform: UNKNOWN
Classifier: Development Status :: 3 - Alpha
Classifier: Intended Audience :: Developers
Classifier: Topic :: Software Development :: Libraries :: Python Modules
Classifier: Topic :: Communications :: Chat
Classifier: License :: OSI Approved :: MIT License
Classifier: Programming Language :: Python :: 3.2
Classifier: Programming Language :: Python :: 3.3
Classifier: Programming Language :: Python :: 3.4
Requires-Dist: requests
